[
    {
        "vars": [
            "MedInc"
        ],
        "stats": [
            {
                "ranges": {
                    "MedHouseVal": "all"
                },
                "stats": {
                    "mi": 0.48270396847627217,
                    "mi-time": 0.1049346923828125,
                    "mi-std": 0.009011155350259632,
                    "linearinfo": 0.3907594551190502,
                    "linearinfo-time": 0.006752967834472656,
                    "linearinfo-std": 0.009166902187498065,
                    "samples": 19648
                }
            },
            {
                "ranges": {
                    "MedHouseVal": "low"
                },
                "stats": {
                    "mi": 0.19182874642788142,
                    "mi-time": 0.1132960319519043,
                    "mi-std": 0.01048213602943513,
                    "linearinfo": 0.14786089351061146,
                    "linearinfo-time": 0.00038504600524902344,
                    "linearinfo-std": 0.008853980032272325,
                    "samples": 7620
                }
            },
            {
                "ranges": {
                    "MedHouseVal": "mid"
                },
                "stats": {
                    "mi": 0.1949497984850299,
                    "mi-time": 0.04163813591003418,
                    "mi-std": 0.008544114071595452,
                    "linearinfo": 0.12819937663259584,
                    "linearinfo-time": 0.0014162063598632812,
                    "linearinfo-std": 0.00716846409536946,
                    "samples": 10511
                }
            },
            {
                "ranges": {
                    "MedHouseVal": "high"
                },
                "stats": {
                    "mi": 0.0520398017088865,
                    "mi-time": 0.019891738891601562,
                    "mi-std": 0.01753310259041835,
                    "linearinfo": 0.020183184648503244,
                    "linearinfo-time": 0.0003712177276611328,
                    "linearinfo-std": 0.005741377736150079,
                    "samples": 1660
                }
            }
        ]
    },
    {
        "vars": [
            "HouseAge"
        ],
        "stats": [
            {
                "ranges": {
                    "MedHouseVal": "all"
                },
                "stats": {
                    "mi": 0.039819753358602314,
                    "mi-time": 0.11855220794677734,
                    "mi-std": 0.004627843538841629,
                    "linearinfo": 0.003067251676139572,
                    "linearinfo-time": 0.0014028549194335938,
                    "linearinfo-std": 0.0005722252703308165,
                    "samples": 19648
                }
            },
            {
                "ranges": {
                    "MedHouseVal": "low"
                },
                "stats": {
                    "mi": 0.041816620271252235,
                    "mi-time": 0.10907578468322754,
                    "mi-std": 0.004312460170895531,
                    "linearinfo": 0.005536142716031219,
                    "linearinfo-time": 0.00037860870361328125,
                    "linearinfo-std": 0.0007050778186367425,
                    "samples": 7620
                }
            },
            {
                "ranges": {
                    "MedHouseVal": "mid"
                },
                "stats": {
                    "mi": 0.018993421515313108,
                    "mi-time": 0.04754948616027832,
                    "mi-std": 0.00434945203440457,
                    "linearinfo": 0.0009946270868749468,
                    "linearinfo-time": 0.001336812973022461,
                    "linearinfo-std": 0.0006603350586306349,
                    "samples": 10511
                }
            },
            {
                "ranges": {
                    "MedHouseVal": "high"
                },
                "stats": {
                    "mi": 0.03796858305255602,
                    "mi-time": 0.021144628524780273,
                    "mi-std": 0.010265169522999239,
                    "linearinfo": 0.0014486542034101236,
                    "linearinfo-time": 0.00035858154296875,
                    "linearinfo-std": 0.0013017720215639944,
                    "samples": 1660
                }
            }
        ]
    },
    {
        "vars": [
            "AveRooms"
        ],
        "stats": [
            {
                "ranges": {
                    "MedHouseVal": "all"
                },
                "stats": {
                    "mi": 0.10582881063470677,
                    "mi-time": 0.10614514350891113,
                    "mi-std": 0.006945643941397552,
                    "linearinfo": 0.009037436449924519,
                    "linearinfo-time": 0.0014157295227050781,
                    "linearinfo-std": 0.0016535070364437257,
                    "samples": 19648
                }
            },
            {
                "ranges": {
                    "MedHouseVal": "low"
                },
                "stats": {
                    "mi": 0.04344297404150236,
                    "mi-time": 0.10189557075500488,
                    "mi-std": 0.00832868291528282,
                    "linearinfo": 0.0003917853578212817,
                    "linearinfo-time": 0.0003876686096191406,
                    "linearinfo-std": 0.0005436289341647075,
                    "samples": 7620
                }
            },
            {
                "ranges": {
                    "MedHouseVal": "mid"
                },
                "stats": {
                    "mi": 0.07623199575182117,
                    "mi-time": 0.04071331024169922,
                    "mi-std": 0.007924855843600141,
                    "linearinfo": 0.006511562980551733,
                    "linearinfo-time": 0.001386404037475586,
                    "linearinfo-std": 0.004236769493725242,
                    "samples": 10511
                }
            },
            {
                "ranges": {
                    "MedHouseVal": "high"
                },
                "stats": {
                    "mi": 0.041437309165876735,
                    "mi-time": 0.020090341567993164,
                    "mi-std": 0.017222718079613175,
                    "linearinfo": 0.003126417048464611,
                    "linearinfo-time": 0.00037741661071777344,
                    "linearinfo-std": 0.002618450076049616,
                    "samples": 1660
                }
            }
        ]
    },
    {
        "vars": [
            "AveBedrms"
        ],
        "stats": [
            {
                "ranges": {
                    "MedHouseVal": "all"
                },
                "stats": {
                    "mi": 0.02568980534873073,
                    "mi-time": 0.10710787773132324,
                    "mi-std": 0.004540644954034058,
                    "linearinfo": 0.0027317436508098587,
                    "linearinfo-time": 0.0016164779663085938,
                    "linearinfo-std": 0.0006236794090831101,
                    "samples": 19648
                }
            },
            {
                "ranges": {
                    "MedHouseVal": "low"
                },
                "stats": {
                    "mi": 0.0031977958730296098,
                    "mi-time": 0.10315561294555664,
                    "mi-std": 0.008152409288815355,
                    "linearinfo": 0.0008201798202078385,
                    "linearinfo-time": 0.0003879070281982422,
                    "linearinfo-std": 0.0005073489186787158,
                    "samples": 7620
                }
            },
            {
                "ranges": {
                    "MedHouseVal": "mid"
                },
                "stats": {
                    "mi": 0.01405968561978663,
                    "mi-time": 0.04197072982788086,
                    "mi-std": 0.005778495769640956,
                    "linearinfo": 0.000795916722972586,
                    "linearinfo-time": 0.0013632774353027344,
                    "linearinfo-std": 0.0004941369154034666,
                    "samples": 10511
                }
            },
            {
                "ranges": {
                    "MedHouseVal": "high"
                },
                "stats": {
                    "mi": -0.00025916069425336165,
                    "mi-time": 0.021068572998046875,
                    "mi-std": 0.01505873969101123,
                    "linearinfo": 3.121758015594334e-05,
                    "linearinfo-time": 0.0003573894500732422,
                    "linearinfo-std": 0.00031343729584315614,
                    "samples": 1660
                }
            }
        ]
    },
    {
        "vars": [
            "Population"
        ],
        "stats": [
            {
                "ranges": {
                    "MedHouseVal": "all"
                },
                "stats": {
                    "mi": 0.011506030682821624,
                    "mi-time": 0.1046595573425293,
                    "mi-std": 0.0054754261192411086,
                    "linearinfo": 0.0004843825263109699,
                    "linearinfo-time": 0.0013947486877441406,
                    "linearinfo-std": 0.0003914971532317228,
                    "samples": 19648
                }
            },
            {
                "ranges": {
                    "MedHouseVal": "low"
                },
                "stats": {
                    "mi": 0.025992081666059926,
                    "mi-time": 0.10275483131408691,
                    "mi-std": 0.009782551026974505,
                    "linearinfo": 0.016824259989693485,
                    "linearinfo-time": 0.00038170814514160156,
                    "linearinfo-std": 0.0014729785604602097,
                    "samples": 7620
                }
            },
            {
                "ranges": {
                    "MedHouseVal": "mid"
                },
                "stats": {
                    "mi": 0.0016922853871102733,
                    "mi-time": 0.041191816329956055,
                    "mi-std": 0.007523257126727959,
                    "linearinfo": 0.0017829272880976106,
                    "linearinfo-time": 0.0013594627380371094,
                    "linearinfo-std": 0.0007863779296722388,
                    "samples": 10511
                }
            },
            {
                "ranges": {
                    "MedHouseVal": "high"
                },
                "stats": {
                    "mi": -0.007833812370927477,
                    "mi-time": 0.02079010009765625,
                    "mi-std": 0.01877141673646915,
                    "linearinfo": 0.00013813437936308285,
                    "linearinfo-time": 0.00035762786865234375,
                    "linearinfo-std": 0.0004697099432391123,
                    "samples": 1660
                }
            }
        ]
    },
    {
        "vars": [
            "AveOccup"
        ],
        "stats": [
            {
                "ranges": {
                    "MedHouseVal": "all"
                },
                "stats": {
                    "mi": 0.08959083331921242,
                    "mi-time": 0.1047053337097168,
                    "mi-std": 0.005398305023975949,
                    "linearinfo": 0.039743863085420425,
                    "linearinfo-time": 0.001413583755493164,
                    "linearinfo-std": 0.002823820254699527,
                    "samples": 19648
                }
            },
            {
                "ranges": {
                    "MedHouseVal": "low"
                },
                "stats": {
                    "mi": 0.026390120972018268,
                    "mi-time": 0.1029057502746582,
                    "mi-std": 0.009122046746167999,
                    "linearinfo": 8.267541184025096e-06,
                    "linearinfo-time": 0.0003807544708251953,
                    "linearinfo-std": 0.00015702705787570926,
                    "samples": 7620
                }
            },
            {
                "ranges": {
                    "MedHouseVal": "mid"
                },
                "stats": {
                    "mi": 0.08465796622138995,
                    "mi-time": 0.04144644737243652,
                    "mi-std": 0.007587137609102038,
                    "linearinfo": 0.041682592754199596,
                    "linearinfo-time": 0.0013911724090576172,
                    "linearinfo-std": 0.005325668191770947,
                    "samples": 10511
                }
            },
            {
                "ranges": {
                    "MedHouseVal": "high"
                },
                "stats": {
                    "mi": -0.0018617862716474424,
                    "mi-time": 0.021208524703979492,
                    "mi-std": 0.01730905034963573,
                    "linearinfo": 0.0028249181540045457,
                    "linearinfo-time": 0.0003490447998046875,
                    "linearinfo-std": 0.001420847045291509,
                    "samples": 1660
                }
            }
        ]
    },
    {
        "vars": [
            "Latitude"
        ],
        "stats": [
            {
                "ranges": {
                    "MedHouseVal": "all"
                },
                "stats": {
                    "mi": 0.5308034747689817,
                    "mi-time": 0.09989738464355469,
                    "mi-std": 0.007975104134103227,
                    "linearinfo": 0.016251563617817176,
                    "linearinfo-time": 0.0015692710876464844,
                    "linearinfo-std": 0.001355808316774697,
                    "samples": 19648
                }
            },
            {
                "ranges": {
                    "MedHouseVal": "low"
                },
                "stats": {
                    "mi": 0.4259679882831899,
                    "mi-time": 0.1007997989654541,
                    "mi-std": 0.009338754881022966,
                    "linearinfo": 0.033409625855038906,
                    "linearinfo-time": 0.0003790855407714844,
                    "linearinfo-std": 0.00326004498825821,
                    "samples": 7620
                }
            },
            {
                "ranges": {
                    "MedHouseVal": "mid"
                },
                "stats": {
                    "mi": 0.23807950938993494,
                    "mi-time": 0.0398104190826416,
                    "mi-std": 0.007718175266933673,
                    "linearinfo": 0.003507743558564927,
                    "linearinfo-time": 0.0013496875762939453,
                    "linearinfo-std": 0.0007843999860541652,
                    "samples": 10511
                }
            },
            {
                "ranges": {
                    "MedHouseVal": "high"
                },
                "stats": {
                    "mi": 0.03674497777832045,
                    "mi-time": 0.020514249801635742,
                    "mi-std": 0.01877330383612979,
                    "linearinfo": 0.000978112134808293,
                    "linearinfo-time": 0.00035190582275390625,
                    "linearinfo-std": 0.0007141298213277057,
                    "samples": 1660
                }
            }
        ]
    },
    {
        "vars": [
            "Longitude"
        ],
        "stats": [
            {
                "ranges": {
                    "MedHouseVal": "all"
                },
                "stats": {
                    "mi": 0.5742319190315022,
                    "mi-time": 0.09968066215515137,
                    "mi-std": 0.008474391081687365,
                    "linearinfo": 0.0015102632943318265,
                    "linearinfo-time": 0.0013947486877441406,
                    "linearinfo-std": 0.0004075545890983844,
                    "samples": 19648
                }
            },
            {
                "ranges": {
                    "MedHouseVal": "low"
                },
                "stats": {
                    "mi": 0.43346105380652294,
                    "mi-time": 0.10069036483764648,
                    "mi-std": 0.009723306673667147,
                    "linearinfo": 0.006457897165180536,
                    "linearinfo-time": 0.0003788471221923828,
                    "linearinfo-std": 0.0010632480160603609,
                    "samples": 7620
                }
            },
            {
                "ranges": {
                    "MedHouseVal": "mid"
                },
                "stats": {
                    "mi": 0.22708692531352076,
                    "mi-time": 0.039629220962524414,
                    "mi-std": 0.007838019424231272,
                    "linearinfo": 0.015627970704564207,
                    "linearinfo-time": 0.001392364501953125,
                    "linearinfo-std": 0.001691448648988031,
                    "samples": 10511
                }
            },
            {
                "ranges": {
                    "MedHouseVal": "high"
                },
                "stats": {
                    "mi": 0.02040605914292894,
                    "mi-time": 0.02017045021057129,
                    "mi-std": 0.016872215839227826,
                    "linearinfo": 0.0008345357971597118,
                    "linearinfo-time": 0.0006787776947021484,
                    "linearinfo-std": 0.0014446935632210405,
                    "samples": 1660
                }
            }
        ]
    },
    {
        "vars": [
            "Noise"
        ],
        "stats": [
            {
                "ranges": {
                    "MedHouseVal": "all"
                },
                "stats": {
                    "mi": 0.0019497228693688051,
                    "mi-time": 0.109283447265625,
                    "mi-std": 0.006403508692920519,
                    "linearinfo": 7.507396754209049e-05,
                    "linearinfo-time": 0.0013980865478515625,
                    "linearinfo-std": 3.0265698315804778e-05,
                    "samples": 19648
                }
            },
            {
                "ranges": {
                    "MedHouseVal": "low"
                },
                "stats": {
                    "mi": 0.008368009176844417,
                    "mi-time": 0.10251235961914062,
                    "mi-std": 0.00818072839588745,
                    "linearinfo": 5.149203903404505e-05,
                    "linearinfo-time": 0.00038123130798339844,
                    "linearinfo-std": 0.000214642021456117,
                    "samples": 7620
                }
            },
            {
                "ranges": {
                    "MedHouseVal": "mid"
                },
                "stats": {
                    "mi": 0.006206850510146446,
                    "mi-time": 0.0413053035736084,
                    "mi-std": 0.0075169705374356945,
                    "linearinfo": 0.00021177864308997857,
                    "linearinfo-time": 0.0014109611511230469,
                    "linearinfo-std": 0.0003207933487350768,
                    "samples": 10511
                }
            },
            {
                "ranges": {
                    "MedHouseVal": "high"
                },
                "stats": {
                    "mi": -0.019446446297805557,
                    "mi-time": 0.020428180694580078,
                    "mi-std": 0.018006732232473892,
                    "linearinfo": 0.0005958668578771409,
                    "linearinfo-time": 0.0003490447998046875,
                    "linearinfo-std": 0.0017590383915087576,
                    "samples": 1660
                }
            }
        ]
    },
    {
        "vars": [
            "HouseAge",
            "MedInc"
        ],
        "stats": [
            {
                "ranges": {
                    "MedHouseVal": "all"
                },
                "stats": {
                    "mi": 0.5845490226335043,
                    "mi-time": 0.534552812576294,
                    "mi-std": 0.004291051197053969,
                    "linearinfo": 0.4397126839607429,
                    "linearinfo-time": 0.045073509216308594,
                    "linearinfo-std": 0.01010575787624936,
                    "samples": 19648
                }
            },
            {
                "ranges": {
                    "MedHouseVal": "low"
                },
                "stats": {
                    "mi": 0.22451828863704312,
                    "mi-time": 0.20476627349853516,
                    "mi-std": 0.0022076766330440486,
                    "linearinfo": 0.14879441149564054,
                    "linearinfo-time": 0.016219615936279297,
                    "linearinfo-std": 0.011161448119362004,
                    "samples": 7620
                }
            },
            {
                "ranges": {
                    "MedHouseVal": "mid"
                },
                "stats": {
                    "mi": 0.23710888496883295,
                    "mi-time": 0.31722259521484375,
                    "mi-std": 0.002686827310977039,
                    "linearinfo": 0.14920946380637015,
                    "linearinfo-time": 0.04486346244812012,
                    "linearinfo-std": 0.005342372281689251,
                    "samples": 10511
                }
            },
            {
                "ranges": {
                    "MedHouseVal": "high"
                },
                "stats": {
                    "mi": 0.05569510159741834,
                    "mi-time": 0.048088788986206055,
                    "mi-std": 0.005016759505935638,
                    "linearinfo": 0.03012855201973697,
                    "linearinfo-time": 0.0015439987182617188,
                    "linearinfo-std": 0.00606462780233378,
                    "samples": 1660
                }
            }
        ]
    },
    {
        "vars": [
            "AveRooms",
            "MedInc"
        ],
        "stats": [
            {
                "ranges": {
                    "MedHouseVal": "all"
                },
                "stats": {
                    "mi": 0.6192463791362445,
                    "mi-time": 0.4875681400299072,
                    "mi-std": 0.008100675339192504,
                    "linearinfo": 0.4045069999473909,
                    "linearinfo-time": 0.047754764556884766,
                    "linearinfo-std": 0.009181962303486155,
                    "samples": 19648
                }
            },
            {
                "ranges": {
                    "MedHouseVal": "low"
                },
                "stats": {
                    "mi": 0.2942128342707409,
                    "mi-time": 0.12078642845153809,
                    "mi-std": 0.007196066592189385,
                    "linearinfo": 0.1533112830028783,
                    "linearinfo-time": 0.001783132553100586,
                    "linearinfo-std": 0.006428189256916222,
                    "samples": 7620
                }
            },
            {
                "ranges": {
                    "MedHouseVal": "mid"
                },
                "stats": {
                    "mi": 0.18367759600464778,
                    "mi-time": 0.13248515129089355,
                    "mi-std": 0.007277172103569783,
                    "linearinfo": 0.13183878562112358,
                    "linearinfo-time": 0.014388084411621094,
                    "linearinfo-std": 0.007442612605256121,
                    "samples": 10511
                }
            },
            {
                "ranges": {
                    "MedHouseVal": "high"
                },
                "stats": {
                    "mi": 0.05550217033649555,
                    "mi-time": 0.05167341232299805,
                    "mi-std": 0.012407873895841304,
                    "linearinfo": 0.020498430762672437,
                    "linearinfo-time": 0.0015904903411865234,
                    "linearinfo-std": 0.0081560168411006,
                    "samples": 1660
                }
            }
        ]
    },
    {
        "vars": [
            "AveBedrms",
            "MedInc"
        ],
        "stats": [
            {
                "ranges": {
                    "MedHouseVal": "all"
                },
                "stats": {
                    "mi": 0.4745230084811225,
                    "mi-time": 0.2527914047241211,
                    "mi-std": 0.00915795531679032,
                    "linearinfo": 0.39121738755919355,
                    "linearinfo-time": 0.03338432312011719,
                    "linearinfo-std": 0.007056516603557492,
                    "samples": 19648
                }
            },
            {
                "ranges": {
                    "MedHouseVal": "low"
                },
                "stats": {
                    "mi": 0.18068346912553462,
                    "mi-time": 0.23882198333740234,
                    "mi-std": 0.009193601938959005,
                    "linearinfo": 0.14832861031213662,
                    "linearinfo-time": 0.0497133731842041,
                    "linearinfo-std": 0.0070730770705295124,
                    "samples": 7620
                }
            },
            {
                "ranges": {
                    "MedHouseVal": "mid"
                },
                "stats": {
                    "mi": 0.1756949957823948,
                    "mi-time": 0.45235252380371094,
                    "mi-std": 0.008821920863042638,
                    "linearinfo": 0.12838953553524285,
                    "linearinfo-time": 0.09750580787658691,
                    "linearinfo-std": 0.005301009737482825,
                    "samples": 10511
                }
            },
            {
                "ranges": {
                    "MedHouseVal": "high"
                },
                "stats": {
                    "mi": 0.018733294177158532,
                    "mi-time": 0.10551810264587402,
                    "mi-std": 0.017134203813531732,
                    "linearinfo": 0.020417689418646405,
                    "linearinfo-time": 0.0015337467193603516,
                    "linearinfo-std": 0.006475268376012752,
                    "samples": 1660
                }
            }
        ]
    },
    {
        "vars": [
            "MedInc",
            "Population"
        ],
        "stats": [
            {
                "ranges": {
                    "MedHouseVal": "all"
                },
                "stats": {
                    "mi": 0.5121357958476307,
                    "mi-time": 0.6462860107421875,
                    "mi-std": 0.00909152944084641,
                    "linearinfo": 0.3907605860623186,
                    "linearinfo-time": 0.06426668167114258,
                    "linearinfo-std": 0.007055946509802497,
                    "samples": 19648
                }
            },
            {
                "ranges": {
                    "MedHouseVal": "low"
                },
                "stats": {
                    "mi": 0.22266137094365973,
                    "mi-time": 0.3181755542755127,
                    "mi-std": 0.008973353591205643,
                    "linearinfo": 0.16168944282076278,
                    "linearinfo-time": 0.002231597900390625,
                    "linearinfo-std": 0.00750333818985151,
                    "samples": 7620
                }
            },
            {
                "ranges": {
                    "MedHouseVal": "mid"
                },
                "stats": {
                    "mi": 0.19838092058082374,
                    "mi-time": 0.1376488208770752,
                    "mi-std": 0.008884315906870624,
                    "linearinfo": 0.13014654706020992,
                    "linearinfo-time": 0.0019502639770507812,
                    "linearinfo-std": 0.004053596178911395,
                    "samples": 10511
                }
            },
            {
                "ranges": {
                    "MedHouseVal": "high"
                },
                "stats": {
                    "mi": 0.05230937478587916,
                    "mi-time": 0.027178525924682617,
                    "mi-std": 0.0158837329569317,
                    "linearinfo": 0.020541236680371614,
                    "linearinfo-time": 0.0004665851593017578,
                    "linearinfo-std": 0.006652871606136505,
                    "samples": 1660
                }
            }
        ]
    },
    {
        "vars": [
            "AveOccup",
            "MedInc"
        ],
        "stats": [
            {
                "ranges": {
                    "MedHouseVal": "all"
                },
                "stats": {
                    "mi": 0.644150208090559,
                    "mi-time": 0.18170833587646484,
                    "mi-std": 0.008782758899168394,
                    "linearinfo": 0.45684094384982454,
                    "linearinfo-time": 0.01917719841003418,
                    "linearinfo-std": 0.008530885531809751,
                    "samples": 19648
                }
            },
            {
                "ranges": {
                    "MedHouseVal": "low"
                },
                "stats": {
                    "mi": 0.25168386784616814,
                    "mi-time": 0.1517341136932373,
                    "mi-std": 0.010033232677687371,
                    "linearinfo": 0.14798607178428172,
                    "linearinfo-time": 0.002127408981323242,
                    "linearinfo-std": 0.006609123469325652,
                    "samples": 7620
                }
            },
            {
                "ranges": {
                    "MedHouseVal": "mid"
                },
                "stats": {
                    "mi": 0.31296709925173394,
                    "mi-time": 0.28262782096862793,
                    "mi-std": 0.009009460612300523,
                    "linearinfo": 0.19942217116332409,
                    "linearinfo-time": 0.043253183364868164,
                    "linearinfo-std": 0.00711597830428225,
                    "samples": 10511
                }
            },
            {
                "ranges": {
                    "MedHouseVal": "high"
                },
                "stats": {
                    "mi": 0.06296619924297817,
                    "mi-time": 0.051375627517700195,
                    "mi-std": 0.016619221029789605,
                    "linearinfo": 0.03567593446953847,
                    "linearinfo-time": 0.0015616416931152344,
                    "linearinfo-std": 0.006481649001444575,
                    "samples": 1660
                }
            }
        ]
    },
    {
        "vars": [
            "Latitude",
            "MedInc"
        ],
        "stats": [
            {
                "ranges": {
                    "MedHouseVal": "all"
                },
                "stats": {
                    "mi": 0.8649893430898344,
                    "mi-time": 0.717200517654419,
                    "mi-std": 0.007924706597086823,
                    "linearinfo": 0.40302272642031384,
                    "linearinfo-time": 0.036835432052612305,
                    "linearinfo-std": 0.00900536617622334,
                    "samples": 19648
                }
            },
            {
                "ranges": {
                    "MedHouseVal": "low"
                },
                "stats": {
                    "mi": 0.591745050039386,
                    "mi-time": 0.21540403366088867,
                    "mi-std": 0.005545823131347582,
                    "linearinfo": 0.18903965321148122,
                    "linearinfo-time": 0.020668506622314453,
                    "linearinfo-std": 0.008299563176743576,
                    "samples": 7620
                }
            },
            {
                "ranges": {
                    "MedHouseVal": "mid"
                },
                "stats": {
                    "mi": 0.3304268055615268,
                    "mi-time": 0.26427555084228516,
                    "mi-std": 0.007248336815516542,
                    "linearinfo": 0.13041012271785413,
                    "linearinfo-time": 0.04367780685424805,
                    "linearinfo-std": 0.0049332851781310775,
                    "samples": 10511
                }
            },
            {
                "ranges": {
                    "MedHouseVal": "high"
                },
                "stats": {
                    "mi": 0.07043704918396013,
                    "mi-time": 0.09936666488647461,
                    "mi-std": 0.012243881138859061,
                    "linearinfo": 0.021304004412666767,
                    "linearinfo-time": 0.0017864704132080078,
                    "linearinfo-std": 0.004535039430381384,
                    "samples": 1660
                }
            }
        ]
    },
    {
        "vars": [
            "Longitude",
            "MedInc"
        ],
        "stats": [
            {
                "ranges": {
                    "MedHouseVal": "all"
                },
                "stats": {
                    "mi": 0.9689072899769641,
                    "mi-time": 0.3850874900817871,
                    "mi-std": 0.008167767355652118,
                    "linearinfo": 0.39273804903721776,
                    "linearinfo-time": 0.002321004867553711,
                    "linearinfo-std": 0.007202350693294445,
                    "samples": 19648
                }
            },
            {
                "ranges": {
                    "MedHouseVal": "low"
                },
                "stats": {
                    "mi": 0.6212732845249495,
                    "mi-time": 0.11318755149841309,
                    "mi-std": 0.005604827906981649,
                    "linearinfo": 0.15433011543133665,
                    "linearinfo-time": 0.00955343246459961,
                    "linearinfo-std": 0.00634608589973357,
                    "samples": 7620
                }
            },
            {
                "ranges": {
                    "MedHouseVal": "mid"
                },
                "stats": {
                    "mi": 0.41312458451377154,
                    "mi-time": 0.18451261520385742,
                    "mi-std": 0.007057480397422775,
                    "linearinfo": 0.14442177769486447,
                    "linearinfo-time": 0.026883840560913086,
                    "linearinfo-std": 0.005182044722313678,
                    "samples": 10511
                }
            },
            {
                "ranges": {
                    "MedHouseVal": "high"
                },
                "stats": {
                    "mi": 0.067437787639929,
                    "mi-time": 0.09549593925476074,
                    "mi-std": 0.011791658622027685,
                    "linearinfo": 0.02081985193417294,
                    "linearinfo-time": 0.0013632774353027344,
                    "linearinfo-std": 0.007336394523014329,
                    "samples": 1660
                }
            }
        ]
    },
    {
        "vars": [
            "MedInc",
            "Noise"
        ],
        "stats": [
            {
                "ranges": {
                    "MedHouseVal": "all"
                },
                "stats": {
                    "mi": 0.46910644093749093,
                    "mi-time": 0.6325840950012207,
                    "mi-std": 0.007653697458576843,
                    "linearinfo": 0.3908360334473006,
                    "linearinfo-time": 0.044558048248291016,
                    "linearinfo-std": 0.009843495212014074,
                    "samples": 19648
                }
            },
            {
                "ranges": {
                    "MedHouseVal": "low"
                },
                "stats": {
                    "mi": 0.18072030787268298,
                    "mi-time": 0.19223761558532715,
                    "mi-std": 0.006653722001716016,
                    "linearinfo": 0.1478754494686795,
                    "linearinfo-time": 0.014089345932006836,
                    "linearinfo-std": 0.008453496428457533,
                    "samples": 7620
                }
            },
            {
                "ranges": {
                    "MedHouseVal": "mid"
                },
                "stats": {
                    "mi": 0.17580373764537405,
                    "mi-time": 0.35366320610046387,
                    "mi-std": 0.006480850097762156,
                    "linearinfo": 0.12828937926143089,
                    "linearinfo-time": 0.04420185089111328,
                    "linearinfo-std": 0.00562596934453455,
                    "samples": 10511
                }
            },
            {
                "ranges": {
                    "MedHouseVal": "high"
                },
                "stats": {
                    "mi": 0.03898139982068226,
                    "mi-time": 0.05005979537963867,
                    "mi-std": 0.01215421879905264,
                    "linearinfo": 0.020449607502445812,
                    "linearinfo-time": 0.0013365745544433594,
                    "linearinfo-std": 0.003801110226414685,
                    "samples": 1660
                }
            }
        ]
    },
    {
        "vars": [
            "AveRooms",
            "HouseAge"
        ],
        "stats": [
            {
                "ranges": {
                    "MedHouseVal": "all"
                },
                "stats": {
                    "mi": 0.18204572139909783,
                    "mi-time": 0.7648274898529053,
                    "mi-std": 0.004000410937842194,
                    "linearinfo": 0.014554774116764582,
                    "linearinfo-time": 0.002346515655517578,
                    "linearinfo-std": 0.002591490999690205,
                    "samples": 19648
                }
            },
            {
                "ranges": {
                    "MedHouseVal": "low"
                },
                "stats": {
                    "mi": 0.06480458774438841,
                    "mi-time": 0.11316823959350586,
                    "mi-std": 0.001832155604687276,
                    "linearinfo": 0.0055809693180313095,
                    "linearinfo-time": 0.010200977325439453,
                    "linearinfo-std": 0.0011450272963068342,
                    "samples": 7620
                }
            },
            {
                "ranges": {
                    "MedHouseVal": "mid"
                },
                "stats": {
                    "mi": 0.11435337953052484,
                    "mi-time": 0.1381242275238037,
                    "mi-std": 0.002775477190798256,
                    "linearinfo": 0.008766863930224043,
                    "linearinfo-time": 0.014387845993041992,
                    "linearinfo-std": 0.005221063450430591,
                    "samples": 10511
                }
            },
            {
                "ranges": {
                    "MedHouseVal": "high"
                },
                "stats": {
                    "mi": 0.043521706116994435,
                    "mi-time": 0.05028057098388672,
                    "mi-std": 0.004405703791842444,
                    "linearinfo": 0.006159005195607031,
                    "linearinfo-time": 0.0015571117401123047,
                    "linearinfo-std": 0.00398229353615708,
                    "samples": 1660
                }
            }
        ]
    },
    {
        "vars": [
            "AveBedrms",
            "HouseAge"
        ],
        "stats": [
            {
                "ranges": {
                    "MedHouseVal": "all"
                },
                "stats": {
                    "mi": 0.07583562456667921,
                    "mi-time": 0.6001842021942139,
                    "mi-std": 0.004553060003879537,
                    "linearinfo": 0.005355795280006945,
                    "linearinfo-time": 0.03960013389587402,
                    "linearinfo-std": 0.00046574708392764535,
                    "samples": 19648
                }
            },
            {
                "ranges": {
                    "MedHouseVal": "low"
                },
                "stats": {
                    "mi": 0.03871579714295225,
                    "mi-time": 0.3693521022796631,
                    "mi-std": 0.004007435530805011,
                    "linearinfo": 0.006883654356857401,
                    "linearinfo-time": 0.03930997848510742,
                    "linearinfo-std": 0.0025775748735603916,
                    "samples": 7620
                }
            },
            {
                "ranges": {
                    "MedHouseVal": "mid"
                },
                "stats": {
                    "mi": 0.03540999361512516,
                    "mi-time": 0.36431241035461426,
                    "mi-std": 0.004260094977820652,
                    "linearinfo": 0.0016827314105416205,
                    "linearinfo-time": 0.03487563133239746,
                    "linearinfo-std": 0.000451980014066867,
                    "samples": 10511
                }
            },
            {
                "ranges": {
                    "MedHouseVal": "high"
                },
                "stats": {
                    "mi": 0.03651194956474737,
                    "mi-time": 0.09860992431640625,
                    "mi-std": 0.009137283122832542,
                    "linearinfo": 0.0015305892797841713,
                    "linearinfo-time": 0.0013434886932373047,
                    "linearinfo-std": 0.0014704832251952124,
                    "samples": 1660
                }
            }
        ]
    },
    {
        "vars": [
            "HouseAge",
            "Population"
        ],
        "stats": [
            {
                "ranges": {
                    "MedHouseVal": "all"
                },
                "stats": {
                    "mi": 0.06294887243019345,
                    "mi-time": 0.9549064636230469,
                    "mi-std": 0.004561808027431463,
                    "linearinfo": 0.004413152231765,
                    "linearinfo-time": 0.02442169189453125,
                    "linearinfo-std": 0.0006277644916553119,
                    "samples": 19648
                }
            },
            {
                "ranges": {
                    "MedHouseVal": "low"
                },
                "stats": {
                    "mi": 0.06006460917931725,
                    "mi-time": 0.2031550407409668,
                    "mi-std": 0.00346474589330083,
                    "linearinfo": 0.019257698539342723,
                    "linearinfo-time": 0.009855270385742188,
                    "linearinfo-std": 0.0018271473059142311,
                    "samples": 7620
                }
            },
            {
                "ranges": {
                    "MedHouseVal": "mid"
                },
                "stats": {
                    "mi": 0.018630528091090358,
                    "mi-time": 0.170302152633667,
                    "mi-std": 0.004086735125357167,
                    "linearinfo": 0.0022121559970599476,
                    "linearinfo-time": 0.01030588150024414,
                    "linearinfo-std": 0.0008123762041510254,
                    "samples": 10511
                }
            },
            {
                "ranges": {
                    "MedHouseVal": "high"
                },
                "stats": {
                    "mi": 0.02641347694133244,
                    "mi-time": 0.03417491912841797,
                    "mi-std": 0.00764135149147899,
                    "linearinfo": 0.0014690436889670685,
                    "linearinfo-time": 0.0006392002105712891,
                    "linearinfo-std": 0.0014684452552123925,
                    "samples": 1660
                }
            }
        ]
    },
    {
        "vars": [
            "AveOccup",
            "HouseAge"
        ],
        "stats": [
            {
                "ranges": {
                    "MedHouseVal": "all"
                },
                "stats": {
                    "mi": 0.18225011591752174,
                    "mi-time": 0.20210480690002441,
                    "mi-std": 0.004693118422982426,
                    "linearinfo": 0.0431967343049631,
                    "linearinfo-time": 0.020427942276000977,
                    "linearinfo-std": 0.0028805432687437947,
                    "samples": 19648
                }
            },
            {
                "ranges": {
                    "MedHouseVal": "low"
                },
                "stats": {
                    "mi": 0.0761205525056232,
                    "mi-time": 0.1375904083251953,
                    "mi-std": 0.0039419728716660355,
                    "linearinfo": 0.005588172025834156,
                    "linearinfo-time": 0.023348569869995117,
                    "linearinfo-std": 0.0011021875176434033,
                    "samples": 7620
                }
            },
            {
                "ranges": {
                    "MedHouseVal": "mid"
                },
                "stats": {
                    "mi": 0.15536172822385136,
                    "mi-time": 0.2758665084838867,
                    "mi-std": 0.004394473027796588,
                    "linearinfo": 0.04256431335648101,
                    "linearinfo-time": 0.029297828674316406,
                    "linearinfo-std": 0.005205568032907693,
                    "samples": 10511
                }
            },
            {
                "ranges": {
                    "MedHouseVal": "high"
                },
                "stats": {
                    "mi": 0.028783640070631205,
                    "mi-time": 0.040418386459350586,
                    "mi-std": 0.009358768977690795,
                    "linearinfo": 0.003477792540983634,
                    "linearinfo-time": 0.0005662441253662109,
                    "linearinfo-std": 0.0019453608488060213,
                    "samples": 1660
                }
            }
        ]
    },
    {
        "vars": [
            "HouseAge",
            "Latitude"
        ],
        "stats": [
            {
                "ranges": {
                    "MedHouseVal": "all"
                },
                "stats": {
                    "mi": 0.47596618584339023,
                    "mi-time": 0.6625447273254395,
                    "mi-std": 0.0036708147871837202,
                    "linearinfo": 0.019477246057052738,
                    "linearinfo-time": 0.0692605972290039,
                    "linearinfo-std": 0.001009427585079377,
                    "samples": 19648
                }
            },
            {
                "ranges": {
                    "MedHouseVal": "low"
                },
                "stats": {
                    "mi": 0.346810082965158,
                    "mi-time": 0.27932310104370117,
                    "mi-std": 0.0016568465536418915,
                    "linearinfo": 0.040325429878019,
                    "linearinfo-time": 0.04783129692077637,
                    "linearinfo-std": 0.0037495353438244824,
                    "samples": 7620
                }
            },
            {
                "ranges": {
                    "MedHouseVal": "mid"
                },
                "stats": {
                    "mi": 0.17572100462253915,
                    "mi-time": 0.3085501194000244,
                    "mi-std": 0.003281483929734318,
                    "linearinfo": 0.00436699655125025,
                    "linearinfo-time": 0.027130603790283203,
                    "linearinfo-std": 0.0010563698309093647,
                    "samples": 10511
                }
            },
            {
                "ranges": {
                    "MedHouseVal": "high"
                },
                "stats": {
                    "mi": 0.08201053610960511,
                    "mi-time": 0.050510406494140625,
                    "mi-std": 0.005324518438584036,
                    "linearinfo": 0.0028060410266964654,
                    "linearinfo-time": 0.0018422603607177734,
                    "linearinfo-std": 0.0026129210343137756,
                    "samples": 1660
                }
            }
        ]
    },
    {
        "vars": [
            "HouseAge",
            "Longitude"
        ],
        "stats": [
            {
                "ranges": {
                    "MedHouseVal": "all"
                },
                "stats": {
                    "mi": 0.5752239823625849,
                    "mi-time": 0.20470333099365234,
                    "mi-std": 0.003929871108296753,
                    "linearinfo": 0.004187519032312558,
                    "linearinfo-time": 0.016142845153808594,
                    "linearinfo-std": 0.0005537243240382405,
                    "samples": 19648
                }
            },
            {
                "ranges": {
                    "MedHouseVal": "low"
                },
                "stats": {
                    "mi": 0.4051332601663398,
                    "mi-time": 0.12115669250488281,
                    "mi-std": 0.0015961674244200548,
                    "linearinfo": 0.011162546270892417,
                    "linearinfo-time": 0.011279821395874023,
                    "linearinfo-std": 0.00194139822777255,
                    "samples": 7620
                }
            },
            {
                "ranges": {
                    "MedHouseVal": "mid"
                },
                "stats": {
                    "mi": 0.2387885284843601,
                    "mi-time": 0.25922083854675293,
                    "mi-std": 0.0028703907914555725,
                    "linearinfo": 0.01597779980275635,
                    "linearinfo-time": 0.00193023681640625,
                    "linearinfo-std": 0.0015260391326952652,
                    "samples": 10511
                }
            },
            {
                "ranges": {
                    "MedHouseVal": "high"
                },
                "stats": {
                    "mi": 0.06660011732724783,
                    "mi-time": 0.021973371505737305,
                    "mi-std": 0.008087396309000346,
                    "linearinfo": 0.002695660986708263,
                    "linearinfo-time": 0.001287221908569336,
                    "linearinfo-std": 0.002731418253107585,
                    "samples": 1660
                }
            }
        ]
    },
    {
        "vars": [
            "HouseAge",
            "Noise"
        ],
        "stats": [
            {
                "ranges": {
                    "MedHouseVal": "all"
                },
                "stats": {
                    "mi": 0.042978950544552946,
                    "mi-time": 0.492412805557251,
                    "mi-std": 0.0037265304900902228,
                    "linearinfo": 0.0031087916954610196,
                    "linearinfo-time": 0.06442451477050781,
                    "linearinfo-std": 0.0007841890135358162,
                    "samples": 19648
                }
            },
            {
                "ranges": {
                    "MedHouseVal": "low"
                },
                "stats": {
                    "mi": 0.03274301891376969,
                    "mi-time": 0.18756794929504395,
                    "mi-std": 0.0016543719929326814,
                    "linearinfo": 0.005538305529447124,
                    "linearinfo-time": 0.014608144760131836,
                    "linearinfo-std": 0.0013662929312931336,
                    "samples": 7620
                }
            },
            {
                "ranges": {
                    "MedHouseVal": "mid"
                },
                "stats": {
                    "mi": 0.030904830949364942,
                    "mi-time": 0.32220911979675293,
                    "mi-std": 0.002812722304401564,
                    "linearinfo": 0.0010265225569780962,
                    "linearinfo-time": 0.03349804878234863,
                    "linearinfo-std": 0.0007573780459417951,
                    "samples": 10511
                }
            },
            {
                "ranges": {
                    "MedHouseVal": "high"
                },
                "stats": {
                    "mi": 0.00165728890623923,
                    "mi-time": 0.0969991683959961,
                    "mi-std": 0.005423447443565227,
                    "linearinfo": 0.0017803112246414252,
                    "linearinfo-time": 0.0013043880462646484,
                    "linearinfo-std": 0.0019106574014932016,
                    "samples": 1660
                }
            }
        ]
    },
    {
        "vars": [
            "AveBedrms",
            "AveRooms"
        ],
        "stats": [
            {
                "ranges": {
                    "MedHouseVal": "all"
                },
                "stats": {
                    "mi": 0.19358880706087447,
                    "mi-time": 0.8405895233154297,
                    "mi-std": 0.007119238427070329,
                    "linearinfo": 0.07268052740440178,
                    "linearinfo-time": 0.0018429756164550781,
                    "linearinfo-std": 0.0023384297350158676,
                    "samples": 19648
                }
            },
            {
                "ranges": {
                    "MedHouseVal": "low"
                },
                "stats": {
                    "mi": 0.0913703701360705,
                    "mi-time": 0.15951824188232422,
                    "mi-std": 0.008111517234317883,
                    "linearinfo": 0.011804294997363416,
                    "linearinfo-time": 0.03452920913696289,
                    "linearinfo-std": 0.002428938367809464,
                    "samples": 7620
                }
            },
            {
                "ranges": {
                    "MedHouseVal": "mid"
                },
                "stats": {
                    "mi": 0.08295675556784458,
                    "mi-time": 0.2657475471496582,
                    "mi-std": 0.008268236677545046,
                    "linearinfo": 0.0364796962936022,
                    "linearinfo-time": 0.01574397087097168,
                    "linearinfo-std": 0.002666188373534364,
                    "samples": 10511
                }
            },
            {
                "ranges": {
                    "MedHouseVal": "high"
                },
                "stats": {
                    "mi": 0.04212994922290572,
                    "mi-time": 0.08972358703613281,
                    "mi-std": 0.015389177199553478,
                    "linearinfo": 0.005936057932701133,
                    "linearinfo-time": 0.0005540847778320312,
                    "linearinfo-std": 0.002753840995357715,
                    "samples": 1660
                }
            }
        ]
    },
    {
        "vars": [
            "AveRooms",
            "Population"
        ],
        "stats": [
            {
                "ranges": {
                    "MedHouseVal": "all"
                },
                "stats": {
                    "mi": 0.13928784224062807,
                    "mi-time": 0.21653485298156738,
                    "mi-std": 0.006951613967290088,
                    "linearinfo": 0.010502420456645534,
                    "linearinfo-time": 0.029761552810668945,
                    "linearinfo-std": 0.0020392247847196366,
                    "samples": 19648
                }
            },
            {
                "ranges": {
                    "MedHouseVal": "low"
                },
                "stats": {
                    "mi": 0.08163852662572985,
                    "mi-time": 0.20195508003234863,
                    "mi-std": 0.007909436179755801,
                    "linearinfo": 0.019148015409670194,
                    "linearinfo-time": 0.02254629135131836,
                    "linearinfo-std": 0.0027100070517329868,
                    "samples": 7620
                }
            },
            {
                "ranges": {
                    "MedHouseVal": "mid"
                },
                "stats": {
                    "mi": 0.08056490406014491,
                    "mi-time": 0.3133127689361572,
                    "mi-std": 0.008087091098243297,
                    "linearinfo": 0.007483054232009746,
                    "linearinfo-time": 0.044162750244140625,
                    "linearinfo-std": 0.003064650062486821,
                    "samples": 10511
                }
            },
            {
                "ranges": {
                    "MedHouseVal": "high"
                },
                "stats": {
                    "mi": 0.003400983428920337,
                    "mi-time": 0.09664320945739746,
                    "mi-std": 0.016149933341402474,
                    "linearinfo": 0.003180459040022261,
                    "linearinfo-time": 0.0010840892791748047,
                    "linearinfo-std": 0.001843238481330096,
                    "samples": 1660
                }
            }
        ]
    },
    {
        "vars": [
            "AveOccup",
            "AveRooms"
        ],
        "stats": [
            {
                "ranges": {
                    "MedHouseVal": "all"
                },
                "stats": {
                    "mi": 0.24806378317221317,
                    "mi-time": 1.016578197479248,
                    "mi-std": 0.007453033540290241,
                    "linearinfo": 0.04800384664203007,
                    "linearinfo-time": 0.031050920486450195,
                    "linearinfo-std": 0.0037072364810150707,
                    "samples": 19648
                }
            },
            {
                "ranges": {
                    "MedHouseVal": "low"
                },
                "stats": {
                    "mi": 0.07058852550153011,
                    "mi-time": 0.213942289352417,
                    "mi-std": 0.008768030585527435,
                    "linearinfo": 0.00039178619834327614,
                    "linearinfo-time": 0.009977340698242188,
                    "linearinfo-std": 0.00028098817696121036,
                    "samples": 7620
                }
            },
            {
                "ranges": {
                    "MedHouseVal": "mid"
                },
                "stats": {
                    "mi": 0.1870828530098946,
                    "mi-time": 0.1725780963897705,
                    "mi-std": 0.008280847308006451,
                    "linearinfo": 0.04989783108988511,
                    "linearinfo-time": 0.03172469139099121,
                    "linearinfo-std": 0.00529827901588001,
                    "samples": 10511
                }
            },
            {
                "ranges": {
                    "MedHouseVal": "high"
                },
                "stats": {
                    "mi": 0.03934855029729639,
                    "mi-time": 0.025609731674194336,
                    "mi-std": 0.01747855278184479,
                    "linearinfo": 0.008805097952325399,
                    "linearinfo-time": 0.00045990943908691406,
                    "linearinfo-std": 0.002749961055558006,
                    "samples": 1660
                }
            }
        ]
    },
    {
        "vars": [
            "AveRooms",
            "Latitude"
        ],
        "stats": [
            {
                "ranges": {
                    "MedHouseVal": "all"
                },
                "stats": {
                    "mi": 0.6195407498979705,
                    "mi-time": 0.16115570068359375,
                    "mi-std": 0.007412674839479854,
                    "linearinfo": 0.028947889900438326,
                    "linearinfo-time": 0.01869034767150879,
                    "linearinfo-std": 0.0033477425876718364,
                    "samples": 19648
                }
            },
            {
                "ranges": {
                    "MedHouseVal": "low"
                },
                "stats": {
                    "mi": 0.42783613568005924,
                    "mi-time": 0.14819574356079102,
                    "mi-std": 0.00562863760293011,
                    "linearinfo": 0.03589361152964894,
                    "linearinfo-time": 0.023412466049194336,
                    "linearinfo-std": 0.0030460820158834936,
                    "samples": 7620
                }
            },
            {
                "ranges": {
                    "MedHouseVal": "mid"
                },
                "stats": {
                    "mi": 0.2755363084996296,
                    "mi-time": 0.25492072105407715,
                    "mi-std": 0.00723326027339229,
                    "linearinfo": 0.00897562097345615,
                    "linearinfo-time": 0.0482640266418457,
                    "linearinfo-std": 0.0034323428172412566,
                    "samples": 10511
                }
            },
            {
                "ranges": {
                    "MedHouseVal": "high"
                },
                "stats": {
                    "mi": 0.09727498078127506,
                    "mi-time": 0.10378599166870117,
                    "mi-std": 0.012726844566870578,
                    "linearinfo": 0.004337156802601308,
                    "linearinfo-time": 0.0012259483337402344,
                    "linearinfo-std": 0.0034999770310501187,
                    "samples": 1660
                }
            }
        ]
    },
    {
        "vars": [
            "AveRooms",
            "Longitude"
        ],
        "stats": [
            {
                "ranges": {
                    "MedHouseVal": "all"
                },
                "stats": {
                    "mi": 0.7561935908301249,
                    "mi-time": 0.3644857406616211,
                    "mi-std": 0.0073615510251651105,
                    "linearinfo": 0.01035550607882934,
                    "linearinfo-time": 0.05347251892089844,
                    "linearinfo-std": 0.002354363541948021,
                    "samples": 19648
                }
            },
            {
                "ranges": {
                    "MedHouseVal": "low"
                },
                "stats": {
                    "mi": 0.46812276865011393,
                    "mi-time": 0.3698852062225342,
                    "mi-std": 0.006001029701839217,
                    "linearinfo": 0.006978170967249213,
                    "linearinfo-time": 0.04752922058105469,
                    "linearinfo-std": 0.0016139909545784797,
                    "samples": 7620
                }
            },
            {
                "ranges": {
                    "MedHouseVal": "mid"
                },
                "stats": {
                    "mi": 0.36364848059464994,
                    "mi-time": 0.3221280574798584,
                    "mi-std": 0.006771314000798162,
                    "linearinfo": 0.021765841048320057,
                    "linearinfo-time": 0.04179096221923828,
                    "linearinfo-std": 0.003733414419223749,
                    "samples": 10511
                }
            },
            {
                "ranges": {
                    "MedHouseVal": "high"
                },
                "stats": {
                    "mi": 0.13242835189566432,
                    "mi-time": 0.1030735969543457,
                    "mi-std": 0.013820831010530587,
                    "linearinfo": 0.003930884346292098,
                    "linearinfo-time": 0.0004563331604003906,
                    "linearinfo-std": 0.0032227608646777295,
                    "samples": 1660
                }
            }
        ]
    },
    {
        "vars": [
            "AveRooms",
            "Noise"
        ],
        "stats": [
            {
                "ranges": {
                    "MedHouseVal": "all"
                },
                "stats": {
                    "mi": 0.09791912585279414,
                    "mi-time": 0.1677393913269043,
                    "mi-std": 0.006534968446350479,
                    "linearinfo": 0.009070506209571581,
                    "linearinfo-time": 0.010227203369140625,
                    "linearinfo-std": 0.0026657633343146656,
                    "samples": 19648
                }
            },
            {
                "ranges": {
                    "MedHouseVal": "low"
                },
                "stats": {
                    "mi": 0.04468927647970515,
                    "mi-time": 0.11498689651489258,
                    "mi-std": 0.005352234483637729,
                    "linearinfo": 0.0003928646788460325,
                    "linearinfo-time": 0.010046958923339844,
                    "linearinfo-std": 0.00029416358431729546,
                    "samples": 7620
                }
            },
            {
                "ranges": {
                    "MedHouseVal": "mid"
                },
                "stats": {
                    "mi": 0.0638297334832113,
                    "mi-time": 0.141845703125,
                    "mi-std": 0.006324185751912963,
                    "linearinfo": 0.006535940729195244,
                    "linearinfo-time": 0.02428889274597168,
                    "linearinfo-std": 0.0021910366626543215,
                    "samples": 10511
                }
            },
            {
                "ranges": {
                    "MedHouseVal": "high"
                },
                "stats": {
                    "mi": -0.010720755953246409,
                    "mi-time": 0.042464256286621094,
                    "mi-std": 0.013033290799694194,
                    "linearinfo": 0.0034519283482525713,
                    "linearinfo-time": 0.0007338523864746094,
                    "linearinfo-std": 0.0026935414889049133,
                    "samples": 1660
                }
            }
        ]
    },
    {
        "vars": [
            "AveBedrms",
            "Population"
        ],
        "stats": [
            {
                "ranges": {
                    "MedHouseVal": "all"
                },
                "stats": {
                    "mi": 0.04267369828583333,
                    "mi-time": 0.639301061630249,
                    "mi-std": 0.0064132564509435715,
                    "linearinfo": 0.0029011815113403087,
                    "linearinfo-time": 0.05243730545043945,
                    "linearinfo-std": 0.0007892676701689326,
                    "samples": 19648
                }
            },
            {
                "ranges": {
                    "MedHouseVal": "low"
                },
                "stats": {
                    "mi": 0.02724180935359294,
                    "mi-time": 0.3524482250213623,
                    "mi-std": 0.008783057340449861,
                    "linearinfo": 0.016830900187147255,
                    "linearinfo-time": 0.0379176139831543,
                    "linearinfo-std": 0.0028545675003319782,
                    "samples": 7620
                }
            },
            {
                "ranges": {
                    "MedHouseVal": "mid"
                },
                "stats": {
                    "mi": -0.00020946070385752553,
                    "mi-time": 0.3831498622894287,
                    "mi-std": 0.0071616268336316975,
                    "linearinfo": 0.0029101672293829197,
                    "linearinfo-time": 0.08017969131469727,
                    "linearinfo-std": 0.0011209450469240481,
                    "samples": 10511
                }
            },
            {
                "ranges": {
                    "MedHouseVal": "high"
                },
                "stats": {
                    "mi": 0.01215107868927212,
                    "mi-time": 0.1098172664642334,
                    "mi-std": 0.01824069839313728,
                    "linearinfo": 0.00015295103548388094,
                    "linearinfo-time": 0.001184225082397461,
                    "linearinfo-std": 0.0008170371167822991,
                    "samples": 1660
                }
            }
        ]
    },
    {
        "vars": [
            "AveBedrms",
            "AveOccup"
        ],
        "stats": [
            {
                "ranges": {
                    "MedHouseVal": "all"
                },
                "stats": {
                    "mi": 0.15061373160424044,
                    "mi-time": 0.68196702003479,
                    "mi-std": 0.005949287419820651,
                    "linearinfo": 0.04459583749212146,
                    "linearinfo-time": 0.02326488494873047,
                    "linearinfo-std": 0.0037106142160515066,
                    "samples": 19648
                }
            },
            {
                "ranges": {
                    "MedHouseVal": "low"
                },
                "stats": {
                    "mi": 0.06285273236933658,
                    "mi-time": 0.12160420417785645,
                    "mi-std": 0.008978887131056148,
                    "linearinfo": 0.0008654363135986265,
                    "linearinfo-time": 0.001199960708618164,
                    "linearinfo-std": 0.0005283451858914595,
                    "samples": 7620
                }
            },
            {
                "ranges": {
                    "MedHouseVal": "mid"
                },
                "stats": {
                    "mi": 0.10675215941906512,
                    "mi-time": 0.0953218936920166,
                    "mi-std": 0.007524033384458114,
                    "linearinfo": 0.04327633166427154,
                    "linearinfo-time": 0.015124797821044922,
                    "linearinfo-std": 0.004563593016675919,
                    "samples": 10511
                }
            },
            {
                "ranges": {
                    "MedHouseVal": "high"
                },
                "stats": {
                    "mi": 0.012210127205974784,
                    "mi-time": 0.1060035228729248,
                    "mi-std": 0.01891432864622184,
                    "linearinfo": 0.0028418083990609994,
                    "linearinfo-time": 0.0006108283996582031,
                    "linearinfo-std": 0.002586636703847806,
                    "samples": 1660
                }
            }
        ]
    },
    {
        "vars": [
            "AveBedrms",
            "Latitude"
        ],
        "stats": [
            {
                "ranges": {
                    "MedHouseVal": "all"
                },
                "stats": {
                    "mi": 0.5281448453326784,
                    "mi-time": 0.2514064311981201,
                    "mi-std": 0.0074792949517471,
                    "linearinfo": 0.018147419671203882,
                    "linearinfo-time": 0.014563798904418945,
                    "linearinfo-std": 0.0013152317678527092,
                    "samples": 19648
                }
            },
            {
                "ranges": {
                    "MedHouseVal": "low"
                },
                "stats": {
                    "mi": 0.38531870763499715,
                    "mi-time": 0.3027358055114746,
                    "mi-std": 0.009178853570566511,
                    "linearinfo": 0.03370723373033432,
                    "linearinfo-time": 0.044274091720581055,
                    "linearinfo-std": 0.00289415185107872,
                    "samples": 7620
                }
            },
            {
                "ranges": {
                    "MedHouseVal": "mid"
                },
                "stats": {
                    "mi": 0.21610509779184806,
                    "mi-time": 0.5194780826568604,
                    "mi-std": 0.008094653626933427,
                    "linearinfo": 0.004532661822440129,
                    "linearinfo-time": 0.06125164031982422,
                    "linearinfo-std": 0.0009320965199306539,
                    "samples": 10511
                }
            },
            {
                "ranges": {
                    "MedHouseVal": "high"
                },
                "stats": {
                    "mi": 0.038326771581658994,
                    "mi-time": 0.06915974617004395,
                    "mi-std": 0.018464877800677872,
                    "linearinfo": 0.0010219741355046903,
                    "linearinfo-time": 0.001302480697631836,
                    "linearinfo-std": 0.0015140101280553112,
                    "samples": 1660
                }
            }
        ]
    },
    {
        "vars": [
            "AveBedrms",
            "Longitude"
        ],
        "stats": [
            {
                "ranges": {
                    "MedHouseVal": "all"
                },
                "stats": {
                    "mi": 0.5743188334584368,
                    "mi-time": 0.5761210918426514,
                    "mi-std": 0.008339803462294286,
                    "linearinfo": 0.004194996053326688,
                    "linearinfo-time": 0.027466535568237305,
                    "linearinfo-std": 0.0009475833046917244,
                    "samples": 19648
                }
            },
            {
                "ranges": {
                    "MedHouseVal": "low"
                },
                "stats": {
                    "mi": 0.4099151619856295,
                    "mi-time": 0.22907328605651855,
                    "mi-std": 0.008705854174035929,
                    "linearinfo": 0.007383842575938251,
                    "linearinfo-time": 0.010055780410766602,
                    "linearinfo-std": 0.0013986492075787607,
                    "samples": 7620
                }
            },
            {
                "ranges": {
                    "MedHouseVal": "mid"
                },
                "stats": {
                    "mi": 0.2068241831752193,
                    "mi-time": 0.18786263465881348,
                    "mi-std": 0.008107864735865214,
                    "linearinfo": 0.0163872796514144,
                    "linearinfo-time": 0.018831968307495117,
                    "linearinfo-std": 0.0025348971382409893,
                    "samples": 10511
                }
            },
            {
                "ranges": {
                    "MedHouseVal": "high"
                },
                "stats": {
                    "mi": -0.01117615440046894,
                    "mi-time": 0.06865501403808594,
                    "mi-std": 0.019384480852899486,
                    "linearinfo": 0.0008598912149150467,
                    "linearinfo-time": 0.00055694580078125,
                    "linearinfo-std": 0.0008649620525092086,
                    "samples": 1660
                }
            }
        ]
    },
    {
        "vars": [
            "AveBedrms",
            "Noise"
        ],
        "stats": [
            {
                "ranges": {
                    "MedHouseVal": "all"
                },
                "stats": {
                    "mi": 0.033715366519165846,
                    "mi-time": 0.4060404300689697,
                    "mi-std": 0.006270854792602765,
                    "linearinfo": 0.002778211888104,
                    "linearinfo-time": 0.03009796142578125,
                    "linearinfo-std": 0.0008801181668885404,
                    "samples": 19648
                }
            },
            {
                "ranges": {
                    "MedHouseVal": "low"
                },
                "stats": {
                    "mi": 0.01280630558024531,
                    "mi-time": 0.22547292709350586,
                    "mi-std": 0.008039234768992997,
                    "linearinfo": 0.0008220742290768978,
                    "linearinfo-time": 0.03592395782470703,
                    "linearinfo-std": 0.000333733290974458,
                    "samples": 7620
                }
            },
            {
                "ranges": {
                    "MedHouseVal": "mid"
                },
                "stats": {
                    "mi": 0.007249479143954837,
                    "mi-time": 0.4010319709777832,
                    "mi-std": 0.007459195408643167,
                    "linearinfo": 0.0008272050835039658,
                    "linearinfo-time": 0.029141902923583984,
                    "linearinfo-std": 0.0004345001885417906,
                    "samples": 10511
                }
            },
            {
                "ranges": {
                    "MedHouseVal": "high"
                },
                "stats": {
                    "mi": -0.0061474592280123625,
                    "mi-time": 0.09075117111206055,
                    "mi-std": 0.01769672149766116,
                    "linearinfo": 0.00038805394745638474,
                    "linearinfo-time": 0.0014271736145019531,
                    "linearinfo-std": 0.000674833061257313,
                    "samples": 1660
                }
            }
        ]
    },
    {
        "vars": [
            "AveOccup",
            "Population"
        ],
        "stats": [
            {
                "ranges": {
                    "MedHouseVal": "all"
                },
                "stats": {
                    "mi": 0.1297775971807283,
                    "mi-time": 0.8676400184631348,
                    "mi-std": 0.0061887493331054325,
                    "linearinfo": 0.04410383091408473,
                    "linearinfo-time": 0.08589410781860352,
                    "linearinfo-std": 0.0034344837976803834,
                    "samples": 19648
                }
            },
            {
                "ranges": {
                    "MedHouseVal": "low"
                },
                "stats": {
                    "mi": 0.08405814484904732,
                    "mi-time": 0.2221076488494873,
                    "mi-std": 0.00867149470642229,
                    "linearinfo": 0.01798777264127663,
                    "linearinfo-time": 0.010433197021484375,
                    "linearinfo-std": 0.0020654674812234084,
                    "samples": 7620
                }
            },
            {
                "ranges": {
                    "MedHouseVal": "mid"
                },
                "stats": {
                    "mi": 0.08167974943255553,
                    "mi-time": 0.28929877281188965,
                    "mi-std": 0.007376245298296103,
                    "linearinfo": 0.04168267312798284,
                    "linearinfo-time": 0.026195526123046875,
                    "linearinfo-std": 0.004310788947369525,
                    "samples": 10511
                }
            },
            {
                "ranges": {
                    "MedHouseVal": "high"
                },
                "stats": {
                    "mi": 0.03582719178793704,
                    "mi-time": 0.05518293380737305,
                    "mi-std": 0.01803485975759066,
                    "linearinfo": 0.0028457668753713054,
                    "linearinfo-time": 0.0005509853363037109,
                    "linearinfo-std": 0.0017156895356719663,
                    "samples": 1660
                }
            }
        ]
    },
    {
        "vars": [
            "Latitude",
            "Population"
        ],
        "stats": [
            {
                "ranges": {
                    "MedHouseVal": "all"
                },
                "stats": {
                    "mi": 0.4888530717468429,
                    "mi-time": 0.5192291736602783,
                    "mi-std": 0.007676341561485602,
                    "linearinfo": 0.016266469024845628,
                    "linearinfo-time": 0.03458690643310547,
                    "linearinfo-std": 0.0013063247005818727,
                    "samples": 19648
                }
            },
            {
                "ranges": {
                    "MedHouseVal": "low"
                },
                "stats": {
                    "mi": 0.38764097971560546,
                    "mi-time": 0.13886761665344238,
                    "mi-std": 0.007759345203866615,
                    "linearinfo": 0.04373693322504995,
                    "linearinfo-time": 0.02328205108642578,
                    "linearinfo-std": 0.004650225425867437,
                    "samples": 7620
                }
            },
            {
                "ranges": {
                    "MedHouseVal": "mid"
                },
                "stats": {
                    "mi": 0.18213262111337117,
                    "mi-time": 0.31233978271484375,
                    "mi-std": 0.00802918138944158,
                    "linearinfo": 0.004801188634602999,
                    "linearinfo-time": 0.0373690128326416,
                    "linearinfo-std": 0.0010320000468524461,
                    "samples": 10511
                }
            },
            {
                "ranges": {
                    "MedHouseVal": "high"
                },
                "stats": {
                    "mi": 0.057436168260631644,
                    "mi-time": 0.1042177677154541,
                    "mi-std": 0.017953801753403026,
                    "linearinfo": 0.0011450771021289858,
                    "linearinfo-time": 0.0013515949249267578,
                    "linearinfo-std": 0.0015011513618830546,
                    "samples": 1660
                }
            }
        ]
    },
    {
        "vars": [
            "Longitude",
            "Population"
        ],
        "stats": [
            {
                "ranges": {
                    "MedHouseVal": "all"
                },
                "stats": {
                    "mi": 0.5682122856244279,
                    "mi-time": 0.5692403316497803,
                    "mi-std": 0.007538838972886567,
                    "linearinfo": 0.0022147452727178853,
                    "linearinfo-time": 0.02898383140563965,
                    "linearinfo-std": 0.0006376445889789172,
                    "samples": 19648
                }
            },
            {
                "ranges": {
                    "MedHouseVal": "low"
                },
                "stats": {
                    "mi": 0.40928900496914755,
                    "mi-time": 0.12232112884521484,
                    "mi-std": 0.008115469045007083,
                    "linearinfo": 0.02070190742102874,
                    "linearinfo-time": 0.027578353881835938,
                    "linearinfo-std": 0.0027817775543574346,
                    "samples": 7620
                }
            },
            {
                "ranges": {
                    "MedHouseVal": "mid"
                },
                "stats": {
                    "mi": 0.22988556069986993,
                    "mi-time": 0.28951358795166016,
                    "mi-std": 0.007807648123387494,
                    "linearinfo": 0.016608311612368754,
                    "linearinfo-time": 0.02984476089477539,
                    "linearinfo-std": 0.0017554453984941927,
                    "samples": 10511
                }
            },
            {
                "ranges": {
                    "MedHouseVal": "high"
                },
                "stats": {
                    "mi": 0.05133719415396916,
                    "mi-time": 0.02827286720275879,
                    "mi-std": 0.01791915349094398,
                    "linearinfo": 0.0009885815462620615,
                    "linearinfo-time": 0.0005686283111572266,
                    "linearinfo-std": 0.001511732360419595,
                    "samples": 1660
                }
            }
        ]
    },
    {
        "vars": [
            "Noise",
            "Population"
        ],
        "stats": [
            {
                "ranges": {
                    "MedHouseVal": "all"
                },
                "stats": {
                    "mi": 0.016973265252567725,
                    "mi-time": 0.18922853469848633,
                    "mi-std": 0.005806201360786618,
                    "linearinfo": 0.000527947175873491,
                    "linearinfo-time": 0.02698373794555664,
                    "linearinfo-std": 0.0003284369110696426,
                    "samples": 19648
                }
            },
            {
                "ranges": {
                    "MedHouseVal": "low"
                },
                "stats": {
                    "mi": 0.026372838912818854,
                    "mi-time": 0.052315711975097656,
                    "mi-std": 0.007114455134063453,
                    "linearinfo": 0.016838686395449273,
                    "linearinfo-time": 0.002068042755126953,
                    "linearinfo-std": 0.0035232565286870492,
                    "samples": 7620
                }
            },
            {
                "ranges": {
                    "MedHouseVal": "mid"
                },
                "stats": {
                    "mi": 0.0002681640263292355,
                    "mi-time": 0.19600224494934082,
                    "mi-std": 0.006552602979770757,
                    "linearinfo": 0.0018093735989373558,
                    "linearinfo-time": 0.013505220413208008,
                    "linearinfo-std": 0.0008206150508433344,
                    "samples": 10511
                }
            },
            {
                "ranges": {
                    "MedHouseVal": "high"
                },
                "stats": {
                    "mi": 0.006962114105147542,
                    "mi-time": 0.045278310775756836,
                    "mi-std": 0.016973956473654843,
                    "linearinfo": 0.00048476730107205297,
                    "linearinfo-time": 0.0013184547424316406,
                    "linearinfo-std": 0.0005091851217406411,
                    "samples": 1660
                }
            }
        ]
    },
    {
        "vars": [
            "AveOccup",
            "Latitude"
        ],
        "stats": [
            {
                "ranges": {
                    "MedHouseVal": "all"
                },
                "stats": {
                    "mi": 0.7064686060892138,
                    "mi-time": 0.9286413192749023,
                    "mi-std": 0.008403505178336566,
                    "linearinfo": 0.06643813065905305,
                    "linearinfo-time": 0.03275036811828613,
                    "linearinfo-std": 0.0037544806024707783,
                    "samples": 19648
                }
            },
            {
                "ranges": {
                    "MedHouseVal": "low"
                },
                "stats": {
                    "mi": 0.5132359818762039,
                    "mi-time": 0.20197224617004395,
                    "mi-std": 0.009715906602939714,
                    "linearinfo": 0.03631547696776292,
                    "linearinfo-time": 0.06021404266357422,
                    "linearinfo-std": 0.0040497728614666195,
                    "samples": 7620
                }
            },
            {
                "ranges": {
                    "MedHouseVal": "mid"
                },
                "stats": {
                    "mi": 0.34411215146092566,
                    "mi-time": 0.296004056930542,
                    "mi-std": 0.008292752931273942,
                    "linearinfo": 0.042976536079147705,
                    "linearinfo-time": 0.040827035903930664,
                    "linearinfo-std": 0.0025655624591918755,
                    "samples": 10511
                }
            },
            {
                "ranges": {
                    "MedHouseVal": "high"
                },
                "stats": {
                    "mi": 0.03441483780071958,
                    "mi-time": 0.07500004768371582,
                    "mi-std": 0.0173459166250597,
                    "linearinfo": 0.003755208530935257,
                    "linearinfo-time": 0.010288000106811523,
                    "linearinfo-std": 0.002973957934316284,
                    "samples": 1660
                }
            }
        ]
    },
    {
        "vars": [
            "AveOccup",
            "Longitude"
        ],
        "stats": [
            {
                "ranges": {
                    "MedHouseVal": "all"
                },
                "stats": {
                    "mi": 0.7611374643098673,
                    "mi-time": 0.9278030395507812,
                    "mi-std": 0.00771694917504385,
                    "linearinfo": 0.0398217187141793,
                    "linearinfo-time": 0.002227306365966797,
                    "linearinfo-std": 0.0034480937141420213,
                    "samples": 19648
                }
            },
            {
                "ranges": {
                    "MedHouseVal": "low"
                },
                "stats": {
                    "mi": 0.5268907981639553,
                    "mi-time": 0.11732840538024902,
                    "mi-std": 0.00914245188729199,
                    "linearinfo": 0.00684070894517159,
                    "linearinfo-time": 0.001499176025390625,
                    "linearinfo-std": 0.0021418839873900957,
                    "samples": 7620
                }
            },
            {
                "ranges": {
                    "MedHouseVal": "mid"
                },
                "stats": {
                    "mi": 0.3536348001996499,
                    "mi-time": 0.1410379409790039,
                    "mi-std": 0.008727670247588006,
                    "linearinfo": 0.05201820260915039,
                    "linearinfo-time": 0.01836681365966797,
                    "linearinfo-std": 0.005746710225567458,
                    "samples": 10511
                }
            },
            {
                "ranges": {
                    "MedHouseVal": "high"
                },
                "stats": {
                    "mi": 0.0016761552529703933,
                    "mi-time": 0.05392789840698242,
                    "mi-std": 0.020020142946753118,
                    "linearinfo": 0.0036538542759987336,
                    "linearinfo-time": 0.0005617141723632812,
                    "linearinfo-std": 0.0016424735527214441,
                    "samples": 1660
                }
            }
        ]
    },
    {
        "vars": [
            "AveOccup",
            "Noise"
        ],
        "stats": [
            {
                "ranges": {
                    "MedHouseVal": "all"
                },
                "stats": {
                    "mi": 0.08078059665409876,
                    "mi-time": 0.2266981601715088,
                    "mi-std": 0.006555540494523668,
                    "linearinfo": 0.03978367758009533,
                    "linearinfo-time": 0.05927324295043945,
                    "linearinfo-std": 0.00281579268920865,
                    "samples": 19648
                }
            },
            {
                "ranges": {
                    "MedHouseVal": "low"
                },
                "stats": {
                    "mi": 0.00774124733983041,
                    "mi-time": 0.23645853996276855,
                    "mi-std": 0.00792749563773969,
                    "linearinfo": 9.632285833267962e-06,
                    "linearinfo-time": 0.028469324111938477,
                    "linearinfo-std": 0.00029946877184751055,
                    "samples": 7620
                }
            },
            {
                "ranges": {
                    "MedHouseVal": "mid"
                },
                "stats": {
                    "mi": 0.09245570917800754,
                    "mi-time": 0.3119020462036133,
                    "mi-std": 0.007619344173109964,
                    "linearinfo": 0.04169858225175205,
                    "linearinfo-time": 0.03082275390625,
                    "linearinfo-std": 0.004558521775843899,
                    "samples": 10511
                }
            },
            {
                "ranges": {
                    "MedHouseVal": "high"
                },
                "stats": {
                    "mi": -0.021487313517870494,
                    "mi-time": 0.10081601142883301,
                    "mi-std": 0.016591440522790237,
                    "linearinfo": 0.0031996975838203138,
                    "linearinfo-time": 0.0012950897216796875,
                    "linearinfo-std": 0.0026016131759261842,
                    "samples": 1660
                }
            }
        ]
    },
    {
        "vars": [
            "Latitude",
            "Longitude"
        ],
        "stats": [
            {
                "ranges": {
                    "MedHouseVal": "all"
                },
                "stats": {
                    "mi": 1.3662914060175604,
                    "mi-time": 0.6051144599914551,
                    "mi-std": 0.008011323321459358,
                    "linearinfo": 0.21077829896505426,
                    "linearinfo-time": 0.03175759315490723,
                    "linearinfo-std": 0.005801014144083407,
                    "samples": 19648
                }
            },
            {
                "ranges": {
                    "MedHouseVal": "low"
                },
                "stats": {
                    "mi": 0.8981742560820183,
                    "mi-time": 0.1891496181488037,
                    "mi-std": 0.007472160730999608,
                    "linearinfo": 0.08937583159289839,
                    "linearinfo-time": 0.028595924377441406,
                    "linearinfo-std": 0.004201275407850725,
                    "samples": 7620
                }
            },
            {
                "ranges": {
                    "MedHouseVal": "mid"
                },
                "stats": {
                    "mi": 0.6577034171910461,
                    "mi-time": 0.29705333709716797,
                    "mi-std": 0.008365286050676367,
                    "linearinfo": 0.06180860158765489,
                    "linearinfo-time": 0.020694494247436523,
                    "linearinfo-std": 0.003731195640812588,
                    "samples": 10511
                }
            },
            {
                "ranges": {
                    "MedHouseVal": "high"
                },
                "stats": {
                    "mi": 0.08652643265870141,
                    "mi-time": 0.024896621704101562,
                    "mi-std": 0.019971969942489492,
                    "linearinfo": 0.001079455314250853,
                    "linearinfo-time": 0.0004515647888183594,
                    "linearinfo-std": 0.0014707930002847442,
                    "samples": 1660
                }
            }
        ]
    },
    {
        "vars": [
            "Latitude",
            "Noise"
        ],
        "stats": [
            {
                "ranges": {
                    "MedHouseVal": "all"
                },
                "stats": {
                    "mi": 0.3724876646730694,
                    "mi-time": 0.16596007347106934,
                    "mi-std": 0.006448041234640667,
                    "linearinfo": 0.016307762439987737,
                    "linearinfo-time": 0.0022280216217041016,
                    "linearinfo-std": 0.001968088556345793,
                    "samples": 19648
                }
            },
            {
                "ranges": {
                    "MedHouseVal": "low"
                },
                "stats": {
                    "mi": 0.27709827381603314,
                    "mi-time": 0.11283469200134277,
                    "mi-std": 0.005156598816030833,
                    "linearinfo": 0.03341380234659688,
                    "linearinfo-time": 0.00939178466796875,
                    "linearinfo-std": 0.0035754932221283074,
                    "samples": 7620
                }
            },
            {
                "ranges": {
                    "MedHouseVal": "mid"
                },
                "stats": {
                    "mi": 0.11740455728739418,
                    "mi-time": 0.13434672355651855,
                    "mi-std": 0.006196124197002686,
                    "linearinfo": 0.003527580164790636,
                    "linearinfo-time": 0.02745819091796875,
                    "linearinfo-std": 0.0008937038045125719,
                    "samples": 10511
                }
            },
            {
                "ranges": {
                    "MedHouseVal": "high"
                },
                "stats": {
                    "mi": -0.012200821646471642,
                    "mi-time": 0.051015377044677734,
                    "mi-std": 0.014555056868069856,
                    "linearinfo": 0.0013590020225959503,
                    "linearinfo-time": 0.0012769699096679688,
                    "linearinfo-std": 0.0012112156658717582,
                    "samples": 1660
                }
            }
        ]
    },
    {
        "vars": [
            "Longitude",
            "Noise"
        ],
        "stats": [
            {
                "ranges": {
                    "MedHouseVal": "all"
                },
                "stats": {
                    "mi": 0.44613843433637285,
                    "mi-time": 0.47566699981689453,
                    "mi-std": 0.006895315165801596,
                    "linearinfo": 0.0015458396592985264,
                    "linearinfo-time": 0.04441952705383301,
                    "linearinfo-std": 0.0006229622617711022,
                    "samples": 19648
                }
            },
            {
                "ranges": {
                    "MedHouseVal": "low"
                },
                "stats": {
                    "mi": 0.30230289579444947,
                    "mi-time": 0.19257116317749023,
                    "mi-std": 0.004881023890592696,
                    "linearinfo": 0.0064598276967299025,
                    "linearinfo-time": 0.035883188247680664,
                    "linearinfo-std": 0.0013903136452340572,
                    "samples": 7620
                }
            },
            {
                "ranges": {
                    "MedHouseVal": "mid"
                },
                "stats": {
                    "mi": 0.14301144018264622,
                    "mi-time": 0.2518348693847656,
                    "mi-std": 0.0064354797197276,
                    "linearinfo": 0.015638709276617493,
                    "linearinfo-time": 0.05476641654968262,
                    "linearinfo-std": 0.0013549956223884363,
                    "samples": 10511
                }
            },
            {
                "ranges": {
                    "MedHouseVal": "high"
                },
                "stats": {
                    "mi": 0.003741837931347634,
                    "mi-time": 0.11534833908081055,
                    "mi-std": 0.015591240202722739,
                    "linearinfo": 0.0012040548504071765,
                    "linearinfo-time": 0.0011518001556396484,
                    "linearinfo-std": 0.001777173722617279,
                    "samples": 1660
                }
            }
        ]
    }
]